MANIFEST.in
README.md
setup.py
chimney/__init__.py
chimney/api.py
chimney/compilers.py
chimney/executor.py
chimney/flags.py
chimney/scheduler.py
chimney/watch.py
chimney.egg-info/PKG-INFO
chimney.egg-info/SOURCES.txt
chimney.egg-info/dependency_links.txt
chimney.egg-info/pbr.json
chimney.egg-info/requires.txt
chimney.egg-info/top_level.txt