Metadata-Version: 1.1
Name: chimney
Version: 0.4
Summary: Compile web assets
Home-page: https://github.com/mrj0/chimney/
Author: Mike Johnson
Author-email: mike@mrj0.com
License: GPL
Platform: UNKNOWN
Classifier: Development Status :: 5 - Production/Stable
